odoo/addons/stock_barcodes_gs1_expiry/README.rst
odoo/addons/stock_barcodes_gs1_expiry/__init__.py
odoo/addons/stock_barcodes_gs1_expiry/__manifest__.py
odoo/addons/stock_barcodes_gs1_expiry/i18n/es.po
odoo/addons/stock_barcodes_gs1_expiry/i18n/stock_barcodes_gs1_expiry.pot
odoo/addons/stock_barcodes_gs1_expiry/readme/CONTRIBUTORS.rst
odoo/addons/stock_barcodes_gs1_expiry/readme/DESCRIPTION.rst
odoo/addons/stock_barcodes_gs1_expiry/readme/USAGE.rst
odoo/addons/stock_barcodes_gs1_expiry/static/description/icon.png
odoo/addons/stock_barcodes_gs1_expiry/static/description/index.html
odoo/addons/stock_barcodes_gs1_expiry/tests/__init__.py
odoo/addons/stock_barcodes_gs1_expiry/tests/test_stock_barcodes_gs1_expiry.py
odoo/addons/stock_barcodes_gs1_expiry/wizard/__init__.py
odoo/addons/stock_barcodes_gs1_expiry/wizard/stock_barcodes_read.py
odoo/addons/stock_barcodes_gs1_expiry/wizard/stock_barcodes_read_views.xml
odoo_addon_stock_barcodes_gs1_expiry-15.0.1.0.0.1.dist-info/METADATA
odoo_addon_stock_barcodes_gs1_expiry-15.0.1.0.0.1.dist-info/WHEEL
odoo_addon_stock_barcodes_gs1_expiry-15.0.1.0.0.1.dist-info/top_level.txt
odoo_addon_stock_barcodes_gs1_expiry-15.0.1.0.0.1.dist-info/RECORD
